DMARCReporting/__init__.py
DMARCReporting/__main__.py
DMARCReporting/cli.py
DMARCReporting/constants.py
DMARCReporting/decompressor.py
DMARCReporting/dns.py
DMARCReporting/filelister.py
DMARCReporting/parser.py
DMARCReporting/renderer.py
DMARCReporting-0.3.0.dist-info/LICENSE
DMARCReporting-0.3.0.dist-info/METADATA
DMARCReporting-0.3.0.dist-info/WHEEL
DMARCReporting-0.3.0.dist-info/entry_points.txt
DMARCReporting-0.3.0.dist-info/top_level.txt
DMARCReporting-0.3.0.dist-info/RECORD
