Metadata-Version: 2.1
Name: DMARCReporting
Version: 0.3.0
Summary: Simple tool to extract error reports from DMARC files
Home-page: https://github.com/MozaicWorks/DMARCReporting
Author: Mozaic Works
Author-email: alex.bolboaca@mozaicworks.com
License: MIT
Classifier: License :: OSI Approved :: MIT License
Classifier: Programming Language :: Python :: 3
Requires-Python: >=3.8
License-File: LICENSE
Requires-Dist: lxml
Requires-Dist: tabulate
